iteda/__init__.py
iteda/iteda.py
iteda-1.0.dist-info/DESCRIPTION.rst
iteda-1.0.dist-info/METADATA
iteda-1.0.dist-info/RECORD
iteda-1.0.dist-info/WHEEL
iteda-1.0.dist-info/metadata.json
iteda-1.0.dist-info/top_level.txt
