Metadata-Version: 2.0
Name: iteda
Version: 1.0
Summary: This is a menu to control an integrating sphere through a serial interface (rs232)
Home-page: https://gitlab.com/fabriziodifran/esfera-codigo-verilog
Author: victor esparza
Author-email: vicmaresparza@gmail.com
License: MIT
Keywords: MENU,UART,SPHERE
Platform: UNKNOWN
Classifier: Development Status :: 4 - Beta
Classifier: Intended Audience :: Developers
Classifier: Topic :: Software Development :: Build Tools
Classifier: License :: OSI Approved :: MIT License
Classifier: Programming Language :: Python :: 2.7
Requires-Dist: numpy
Requires-Dist: pyserial
Requires-Dist: argparse
Requires-Dist: serial
